hfdol/__init__.py
hfdol/base.py
hfdol/tests/__init__.py
hfdol/tests/test_base.py
hfdol-0.1.17.dist-info/licenses/LICENSE
hfdol-0.1.17.dist-info/METADATA
hfdol-0.1.17.dist-info/WHEEL
hfdol-0.1.17.dist-info/top_level.txt
hfdol-0.1.17.dist-info/RECORD
