Metadata-Version: 2.4
Name: hfdol
Version: 0.1.17
Summary: Simple Mapping interface to HuggingFace
Home-page: https://github.com/thorwhalen/hfdol
Author: Thor Whalen
License: mit
Keywords: datasets,data science,artificial intelligence,AI
Platform: any
License-File: LICENSE
Requires-Dist: datasets
Requires-Dist: huggingface
Provides-Extra: testing
Dynamic: license-file
